<?xml version="1.0" encoding="UTF-8"?>
<document filename="cTDaR_t10285.jpg">
    <table>
        <Coords points="53,113 53,626 736,626 736,113"/>
        <cell id="0" neighbors="1:B">
            <Coords points="54,145 93,145 93,156 54,156"/>
        </cell>
        <cell id="1" neighbors="0:T 2:B 22:R">
            <Coords points="56,200 117,200 117,240 56,240"/>
        </cell>
        <cell id="2" neighbors="1:T 3:B 23:R">
            <Coords points="55,247 101,247 101,257 55,257"/>
        </cell>
        <cell id="3" neighbors="2:T 19:B 24:R">
            <Coords points="56,264 113,264 113,289 56,289"/>
        </cell>
        <cell id="4" neighbors="5:B 6:B 7:B 59:R">
            <Coords points="142,156 277,156 277,169 142,169"/>
        </cell>
        <cell id="5" neighbors="4:T 6:R 11:B">
            <Coords points="142,172 174,172 174,182 142,182"/>
        </cell>
        <cell id="6" neighbors="4:T 5:L 7:R 12:B">
            <Coords points="184,171 215,171 215,182 184,182"/>
        </cell>
        <cell id="7" neighbors="4:T 6:L 8:R 10:B">
            <Coords points="223,172 255,172 255,182 223,182"/>
        </cell>
        <cell id="8" neighbors="7:L 9:B 13:R">
            <Coords points="265,170 292,170 292,180 265,180"/>
        </cell>
        <cell id="9" neighbors="8:T 10:L 18:R 45:B">
            <Coords points="280,186 292,186 292,195 280,195"/>
        </cell>
        <cell id="10" neighbors="7:T 9:R 12:L 43:B">
            <Coords points="242,187 255,187 255,196 242,196"/>
        </cell>
        <cell id="11" neighbors="5:T 12:R 22:B">
            <Coords points="161,187 176,187 176,196 161,196"/>
        </cell>
        <cell id="12" neighbors="6:T 10:R 11:L 37:B">
            <Coords points="202,187 216,187 216,196 202,196"/>
        </cell>
        <cell id="13" neighbors="8:L 14:R 18:B">
            <Coords points="328,173 351,173 351,180 328,180"/>
        </cell>
        <cell id="14" neighbors="13:L 15:R 17:B">
            <Coords points="356,171 388,171 388,182 356,182"/>
        </cell>
        <cell id="15" neighbors="14:L 16:B 59:T 61:R">
            <Coords points="397,173 428,173 428,181 397,181"/>
        </cell>
        <cell id="16" neighbors="15:T 17:L 49:B 72:R">
            <Coords points="415,187 428,187 428,196 415,196"/>
        </cell>
        <cell id="17" neighbors="14:T 16:R 18:L 48:B">
            <Coords points="375,187 389,187 389,196 375,196"/>
        </cell>
        <cell id="18" neighbors="9:L 13:T 17:R 47:B">
            <Coords points="336,187 349,187 349,195 336,195"/>
        </cell>
        <cell id="19" neighbors="3:T 20:B 25:R">
            <Coords points="56,297 110,297 110,323 56,323"/>
        </cell>
        <cell id="20" neighbors="19:T 21:B 26:R">
            <Coords points="56,330 117,330 117,370 56,370"/>
        </cell>
        <cell id="21" neighbors="20:T 27:R 176:B">
            <Coords points="56,376 117,376 117,417 56,417"/>
        </cell>
        <cell id="22" neighbors="1:L 11:T 23:B 37:R">
            <Coords points="138,232 175,232 175,241 138,241"/>
        </cell>
        <cell id="23" neighbors="2:L 22:T 24:B 38:R">
            <Coords points="138,247 175,247 175,257 138,257"/>
        </cell>
        <cell id="24" neighbors="3:L 23:T 25:B 39:R">
            <Coords points="137,280 175,280 175,290 137,290"/>
        </cell>
        <cell id="25" neighbors="19:L 24:T 26:B 40:R">
            <Coords points="144,315 176,315 176,324 144,324"/>
        </cell>
        <cell id="26" neighbors="20:L 25:T 27:B 28:R">
            <Coords points="142,361 175,361 175,371 142,371"/>
        </cell>
        <cell id="27" neighbors="21:L 26:T 29:R 183:B">
            <Coords points="139,408 175,408 175,417 139,417"/>
        </cell>
        <cell id="28" neighbors="26:L 29:B 31:R 40:T">
            <Coords points="199,360 217,360 217,370 199,370"/>
        </cell>
        <cell id="29" neighbors="27:L 28:T 30:R 184:B">
            <Coords points="192,408 216,408 216,418 192,418"/>
        </cell>
        <cell id="30" neighbors="29:L 35:R 41:T 185:B">
            <Coords points="239,408 257,408 257,416 239,416"/>
        </cell>
        <cell id="31" neighbors="28:L 32:R 35:B 56:T">
            <Coords points="317,360 351,360 351,370 317,370"/>
        </cell>
        <cell id="32" neighbors="31:L 33:R 36:B 57:T">
            <Coords points="375,361 393,361 393,371 375,371"/>
        </cell>
        <cell id="33" neighbors="32:L 34:B 54:T 83:R">
            <Coords points="421,361 434,361 434,372 421,372"/>
        </cell>
        <cell id="34" neighbors="33:T 36:L 81:R 122:B">
            <Coords points="421,408 433,408 433,418 421,418"/>
        </cell>
        <cell id="35" neighbors="30:L 31:T 36:R 194:B">
            <Coords points="313,408 350,408 350,418 313,418"/>
        </cell>
        <cell id="36" neighbors="32:T 34:R 35:L 112:B">
            <Coords points="376,407 393,407 393,418 376,418"/>
        </cell>
        <cell id="37" neighbors="12:T 22:L 38:B 43:R">
            <Coords points="185,232 217,232 217,241 185,241"/>
        </cell>
        <cell id="38" neighbors="23:L 37:T 39:B 44:R">
            <Coords points="186,246 217,246 217,256 186,256"/>
        </cell>
        <cell id="39" neighbors="24:L 38:T 40:B 42:R">
            <Coords points="184,280 216,280 216,289 184,289"/>
        </cell>
        <cell id="40" neighbors="25:L 28:B 39:T 41:R">
            <Coords points="192,314 217,314 217,324 192,324"/>
        </cell>
        <cell id="41" neighbors="30:B 40:L 42:T 56:R">
            <Coords points="239,314 256,314 256,324 239,324"/>
        </cell>
        <cell id="42" neighbors="39:L 41:B 44:T 46:R">
            <Coords points="230,280 256,280 256,289 230,289"/>
        </cell>
        <cell id="43" neighbors="10:T 37:L 44:B 45:R">
            <Coords points="226,232 257,232 257,241 226,241"/>
        </cell>
        <cell id="44" neighbors="38:L 42:B 43:T 50:R">
            <Coords points="231,247 255,247 255,257 231,257"/>
        </cell>
        <cell id="45" neighbors="9:T 43:L 46:B 47:R">
            <Coords points="276,232 295,232 295,241 276,241"/>
        </cell>
        <cell id="46" neighbors="42:L 45:T 55:R 186:B">
            <Coords points="276,280 294,280 294,288 276,288"/>
        </cell>
        <cell id="47" neighbors="18:T 45:L 48:R 50:B">
            <Coords points="312,231 349,231 349,241 312,241"/>
        </cell>
        <cell id="48" neighbors="17:T 47:L 49:R 51:B">
            <Coords points="362,232 394,232 394,241 362,241"/>
        </cell>
        <cell id="49" neighbors="16:T 48:L 52:B 77:R">
            <Coords points="403,231 433,231 433,241 403,241"/>
        </cell>
        <cell id="50" neighbors="44:L 47:T 51:R 55:B">
            <Coords points="313,247 350,247 350,255 313,255"/>
        </cell>
        <cell id="51" neighbors="48:T 50:L 52:R 58:B">
            <Coords points="369,247 392,247 392,257 369,257"/>
        </cell>
        <cell id="52" neighbors="49:T 51:L 53:B 78:R">
            <Coords points="402,247 434,247 434,257 402,257"/>
        </cell>
        <cell id="53" neighbors="52:T 54:B 58:L 79:R">
            <Coords points="410,280 434,280 434,289 410,289"/>
        </cell>
        <cell id="54" neighbors="33:B 53:T 57:L 80:R">
            <Coords points="415,314 433,314 433,324 415,324"/>
        </cell>
        <cell id="55" neighbors="46:L 50:T 56:B 58:R">
            <Coords points="313,279 350,279 350,289 313,289"/>
        </cell>
        <cell id="56" neighbors="31:B 41:L 55:T 57:R">
            <Coords points="319,314 350,314 350,324 319,324"/>
        </cell>
        <cell id="57" neighbors="32:B 54:R 56:L 58:T">
            <Coords points="375,314 393,314 393,324 375,324"/>
        </cell>
        <cell id="58" neighbors="51:T 53:R 55:L 57:B">
            <Coords points="368,279 392,279 392,290 368,290"/>
        </cell>
        <cell id="59" neighbors="4:L 15:B 60:R 61:B">
            <Coords points="392,158 469,158 469,167 392,167"/>
        </cell>
        <cell id="60" neighbors="59:L 65:B 66:B">
            <Coords points="593,158 661,158 661,168 593,168"/>
        </cell>
        <cell id="61" neighbors="15:L 59:T 62:R 72:B">
            <Coords points="436,172 468,172 468,181 436,181"/>
        </cell>
        <cell id="62" neighbors="61:L 63:R 73:B">
            <Coords points="477,170 505,170 505,181 477,181"/>
        </cell>
        <cell id="63" neighbors="62:L 64:R 76:B">
            <Coords points="521,172 543,172 543,180 521,180"/>
        </cell>
        <cell id="64" neighbors="63:L 65:R 71:B">
            <Coords points="551,171 582,171 582,181 551,181"/>
        </cell>
        <cell id="65" neighbors="60:T 64:L 66:R 70:B">
            <Coords points="592,172 623,172 623,182 592,182"/>
        </cell>
        <cell id="66" neighbors="60:T 65:L 67:R 69:B">
            <Coords points="635,172 667,172 667,183 635,183"/>
        </cell>
        <cell id="67" neighbors="66:L 68:B 74:R">
            <Coords points="674,170 702,170 702,181 674,181"/>
        </cell>
        <cell id="68" neighbors="67:T 69:L 75:R 106:B">
            <Coords points="694,187 702,187 702,196 694,196"/>
        </cell>
        <cell id="69" neighbors="66:T 68:R 70:L 101:B">
            <Coords points="658,187 667,187 667,194 658,194"/>
        </cell>
        <cell id="70" neighbors="65:T 69:R 71:L 97:B">
            <Coords points="614,187 624,187 624,195 614,195"/>
        </cell>
        <cell id="71" neighbors="64:T 70:R 76:L 91:B">
            <Coords points="575,187 584,187 584,196 575,196"/>
        </cell>
        <cell id="72" neighbors="16:L 61:T 73:R 77:B">
            <Coords points="454,187 469,187 469,196 454,196"/>
        </cell>
        <cell id="73" neighbors="62:T 72:L 76:R 87:B">
            <Coords points="492,187 506,187 506,195 492,195"/>
        </cell>
        <cell id="74" neighbors="67:L 75:B">
            <Coords points="711,172 732,172 732,180 711,180"/>
        </cell>
        <cell id="75" neighbors="68:L 74:T 107:B">
            <Coords points="723,187 732,187 732,194 723,194"/>
        </cell>
        <cell id="76" neighbors="63:T 71:R 73:L 90:B">
            <Coords points="528,186 543,186 543,196 528,196"/>
        </cell>
        <cell id="77" neighbors="49:L 72:T 78:B 87:R">
            <Coords points="442,232 473,232 473,242 442,242"/>
        </cell>
        <cell id="78" neighbors="52:L 77:T 79:B 92:R">
            <Coords points="442,247 473,247 473,257 442,257"/>
        </cell>
        <cell id="79" neighbors="53:L 78:T 80:B 88:R">
            <Coords points="441,281 473,281 473,289 441,289"/>
        </cell>
        <cell id="80" neighbors="54:L 79:T 81:B 96:R">
            <Coords points="455,314 474,314 474,325 455,325"/>
        </cell>
        <cell id="81" neighbors="34:L 80:T 82:R 127:B">
            <Coords points="456,408 474,408 474,419 456,419"/>
        </cell>
        <cell id="82" neighbors="81:L 83:T 85:R 130:B">
            <Coords points="528,407 546,407 546,417 528,417"/>
        </cell>
        <cell id="83" neighbors="33:L 82:B 84:R 96:T">
            <Coords points="529,360 546,360 546,371 529,371"/>
        </cell>
        <cell id="84" neighbors="83:L 85:B 98:T">
            <Coords points="610,361 625,361 625,370 610,370"/>
        </cell>
        <cell id="85" neighbors="82:L 84:T 86:R 145:B">
            <Coords points="610,409 625,409 625,416 610,416"/>
        </cell>
        <cell id="86" neighbors="85:L 104:T 146:B">
            <Coords points="648,409 668,409 668,417 648,417"/>
        </cell>
        <cell id="87" neighbors="73:T 77:L 88:B 90:R">
            <Coords points="486,232 509,232 509,241 486,241"/>
        </cell>
        <cell id="88" neighbors="79:L 87:T 89:R 142:B">
            <Coords points="485,280 509,280 509,289 485,289"/>
        </cell>
        <cell id="89" neighbors="88:L 92:T 94:R 96:B">
            <Coords points="514,280 546,280 546,289 514,289"/>
        </cell>
        <cell id="90" neighbors="76:T 87:L 91:R 92:B">
            <Coords points="514,232 547,232 547,241 514,241"/>
        </cell>
        <cell id="91" neighbors="71:T 90:L 93:B 97:R">
            <Coords points="570,232 584,232 584,240 570,240"/>
        </cell>
        <cell id="92" neighbors="78:L 89:B 90:T 93:R">
            <Coords points="515,247 545,247 545,257 515,257"/>
        </cell>
        <cell id="93" neighbors="91:T 92:L 94:B 100:R">
            <Coords points="569,247 584,247 584,256 569,256"/>
        </cell>
        <cell id="94" neighbors="89:L 93:T 95:B 99:R">
            <Coords points="569,280 584,280 584,289 569,289"/>
        </cell>
        <cell id="95" neighbors="94:T 96:L 98:R 148:B">
            <Coords points="569,315 584,315 584,323 569,323"/>
        </cell>
        <cell id="96" neighbors="80:L 83:B 89:T 95:R">
            <Coords points="523,314 546,314 546,324 523,324"/>
        </cell>
        <cell id="97" neighbors="70:T 91:L 100:B 101:R">
            <Coords points="611,232 625,232 625,240 611,240"/>
        </cell>
        <cell id="98" neighbors="84:B 95:L 99:T 104:R">
            <Coords points="611,314 626,314 626,323 611,323"/>
        </cell>
        <cell id="99" neighbors="94:L 98:B 100:T 103:R">
            <Coords points="611,280 625,280 625,289 611,289"/>
        </cell>
        <cell id="100" neighbors="93:L 97:T 99:B 102:R">
            <Coords points="610,247 625,247 625,256 610,256"/>
        </cell>
        <cell id="101" neighbors="69:T 97:L 102:B 106:R">
            <Coords points="647,231 667,231 667,241 647,241"/>
        </cell>
        <cell id="102" neighbors="100:L 101:T 103:B 108:R">
            <Coords points="647,247 666,247 666,256 647,256"/>
        </cell>
        <cell id="103" neighbors="99:L 102:T 104:B 105:R">
            <Coords points="647,279 667,279 667,288 647,288"/>
        </cell>
        <cell id="104" neighbors="86:B 98:L 103:T 110:R">
            <Coords points="647,315 669,315 669,323 647,323"/>
        </cell>
        <cell id="105" neighbors="103:L 106:T 109:R 168:B">
            <Coords points="683,280 704,280 704,289 683,289"/>
        </cell>
        <cell id="106" neighbors="68:T 101:L 105:B 107:R">
            <Coords points="683,232 703,232 703,241 683,241"/>
        </cell>
        <cell id="107" neighbors="75:T 106:L 108:B">
            <Coords points="718,232 733,232 733,241 718,241"/>
        </cell>
        <cell id="108" neighbors="102:L 107:T 109:B">
            <Coords points="718,247 732,247 732,256 718,256"/>
        </cell>
        <cell id="109" neighbors="105:L 108:T 110:B">
            <Coords points="718,280 732,280 732,289 718,289"/>
        </cell>
        <cell id="110" neighbors="104:L 109:T 111:B">
            <Coords points="718,314 733,314 733,323 718,323"/>
        </cell>
        <cell id="111" neighbors="110:T 146:L 151:B">
            <Coords points="719,442 731,442 731,451 719,451"/>
        </cell>
        <cell id="112" neighbors="36:T 113:B 122:R 194:L">
            <Coords points="370,443 393,443 393,452 370,452"/>
        </cell>
        <cell id="113" neighbors="112:T 114:B 123:R 195:L">
            <Coords points="376,458 393,458 393,468 376,468"/>
        </cell>
        <cell id="114" neighbors="113:T 115:B 124:R 196:L">
            <Coords points="370,491 393,491 393,500 370,500"/>
        </cell>
        <cell id="115" neighbors="114:T 116:B 125:R 197:L">
            <Coords points="381,506 393,506 393,516 381,516"/>
        </cell>
        <cell id="116" neighbors="115:T 117:B 126:R 198:L">
            <Coords points="376,528 393,528 393,539 376,539"/>
        </cell>
        <cell id="117" neighbors="116:T 118:B 135:R 199:L">
            <Coords points="381,545 393,545 393,554 381,554"/>
        </cell>
        <cell id="118" neighbors="117:T 119:B 120:R 200:L">
            <Coords points="375,574 393,574 393,584 375,584"/>
        </cell>
        <cell id="119" neighbors="118:T 121:R 169:B 201:L">
            <Coords points="382,589 392,589 392,600 382,600"/>
        </cell>
        <cell id="120" neighbors="118:L 121:B 126:T 138:R">
            <Coords points="416,575 433,575 433,584 416,584"/>
        </cell>
        <cell id="121" neighbors="119:L 120:T 139:R 140:B">
            <Coords points="421,590 433,590 433,600 421,600"/>
        </cell>
        <cell id="122" neighbors="34:T 112:L 123:B 127:R">
            <Coords points="410,443 432,443 432,451 410,451"/>
        </cell>
        <cell id="123" neighbors="113:L 122:T 124:B 131:R">
            <Coords points="421,458 433,458 433,468 421,468"/>
        </cell>
        <cell id="124" neighbors="114:L 123:T 125:B 128:R">
            <Coords points="410,490 433,490 433,500 410,500"/>
        </cell>
        <cell id="125" neighbors="115:L 124:T 126:B 133:R">
            <Coords points="421,506 433,506 433,516 421,516"/>
        </cell>
        <cell id="126" neighbors="116:L 120:B 125:T 129:R">
            <Coords points="415,529 433,529 433,539 415,539"/>
        </cell>
        <cell id="127" neighbors="81:T 122:L 128:B 130:R">
            <Coords points="455,443 473,443 473,453 455,453"/>
        </cell>
        <cell id="128" neighbors="124:L 127:T 129:B 132:R">
            <Coords points="455,490 473,490 473,501 455,501"/>
        </cell>
        <cell id="129" neighbors="126:L 128:T 134:R 138:B">
            <Coords points="456,529 473,529 473,539 456,539"/>
        </cell>
        <cell id="130" neighbors="82:T 127:L 131:B 145:R">
            <Coords points="522,442 547,442 547,452 522,452"/>
        </cell>
        <cell id="131" neighbors="123:L 130:T 132:B 147:R">
            <Coords points="529,457 547,457 547,469 529,469"/>
        </cell>
        <cell id="132" neighbors="128:L 131:T 133:B 148:R">
            <Coords points="523,490 546,490 546,499 523,499"/>
        </cell>
        <cell id="133" neighbors="125:L 132:T 134:B 161:R">
            <Coords points="534,506 546,506 546,516 534,516"/>
        </cell>
        <cell id="134" neighbors="129:L 133:T 135:B 157:R">
            <Coords points="529,529 546,529 546,539 529,539"/>
        </cell>
        <cell id="135" neighbors="117:L 134:T 136:B 158:R">
            <Coords points="534,544 546,544 546,554 534,554"/>
        </cell>
        <cell id="136" neighbors="135:T 137:B 138:L 159:R">
            <Coords points="528,574 546,574 546,584 528,584"/>
        </cell>
        <cell id="137" neighbors="136:T 139:L 143:B 162:R">
            <Coords points="533,590 546,590 546,599 533,599"/>
        </cell>
        <cell id="138" neighbors="120:L 129:T 136:R 139:B">
            <Coords points="456,574 473,574 473,583 456,583"/>
        </cell>
        <cell id="139" neighbors="121:L 137:R 138:T 141:B">
            <Coords points="461,589 473,589 473,599 461,599"/>
        </cell>
        <cell id="140" neighbors="121:T 141:R 169:L">
            <Coords points="401,613 433,613 433,623 401,623"/>
        </cell>
        <cell id="141" neighbors="139:T 140:L 142:R">
            <Coords points="440,612 472,612 472,623 440,623"/>
        </cell>
        <cell id="142" neighbors="88:T 141:L 143:R">
            <Coords points="485,613 509,613 509,623 485,623"/>
        </cell>
        <cell id="143" neighbors="137:T 142:L 144:R">
            <Coords points="515,613 547,613 547,623 515,623"/>
        </cell>
        <cell id="144" neighbors="143:L 159:T 163:R">
            <Coords points="569,613 584,613 584,621 569,621"/>
        </cell>
        <cell id="145" neighbors="85:T 130:L 146:R 147:B">
            <Coords points="611,442 625,442 625,452 611,452"/>
        </cell>
        <cell id="146" neighbors="86:T 111:R 145:L 150:B">
            <Coords points="653,441 667,441 667,451 653,451"/>
        </cell>
        <cell id="147" neighbors="131:L 145:T 149:B">
            <Coords points="609,458 624,458 624,466 609,466"/>
        </cell>
        <cell id="148" neighbors="95:T 132:L 149:R 157:B">
            <Coords points="569,490 583,490 583,499 569,499"/>
        </cell>
        <cell id="149" neighbors="147:T 148:L 150:R 161:B">
            <Coords points="610,490 625,490 625,500 610,500"/>
        </cell>
        <cell id="150" neighbors="146:T 149:L 151:R 164:B">
            <Coords points="651,490 667,490 667,500 651,500"/>
        </cell>
        <cell id="151" neighbors="111:T 150:L 152:B">
            <Coords points="718,490 732,490 732,499 718,499"/>
        </cell>
        <cell id="152" neighbors="151:T 153:B 164:L">
            <Coords points="717,529 733,529 733,538 717,538"/>
        </cell>
        <cell id="153" neighbors="152:T 154:B 158:L">
            <Coords points="717,545 732,545 732,552 717,552"/>
        </cell>
        <cell id="154" neighbors="153:T 155:B 165:L">
            <Coords points="717,574 733,574 733,584 717,584"/>
        </cell>
        <cell id="155" neighbors="154:T 156:B 166:L">
            <Coords points="717,591 732,591 732,599 717,599"/>
        </cell>
        <cell id="156" neighbors="155:T 168:L">
            <Coords points="717,613 734,613 734,623 717,623"/>
        </cell>
        <cell id="157" neighbors="134:L 148:T 158:B 164:R">
            <Coords points="570,529 583,529 583,538 570,538"/>
        </cell>
        <cell id="158" neighbors="135:L 153:R 157:T 159:B">
            <Coords points="569,545 584,545 584,554 569,554"/>
        </cell>
        <cell id="159" neighbors="136:L 144:B 158:T 160:R">
            <Coords points="569,574 584,574 584,583 569,583"/>
        </cell>
        <cell id="160" neighbors="159:L 161:T 162:B 165:R">
            <Coords points="611,574 625,574 625,584 611,584"/>
        </cell>
        <cell id="161" neighbors="133:L 149:T 160:B">
            <Coords points="611,506 625,506 625,515 611,515"/>
        </cell>
        <cell id="162" neighbors="137:L 160:T 163:B 166:R">
            <Coords points="611,590 626,590 626,599 611,599"/>
        </cell>
        <cell id="163" neighbors="144:L 162:T 167:R">
            <Coords points="610,612 625,612 625,623 610,623"/>
        </cell>
        <cell id="164" neighbors="150:T 152:R 157:L 165:B">
            <Coords points="648,529 667,529 667,538 648,538"/>
        </cell>
        <cell id="165" neighbors="154:R 160:L 164:T 166:B">
            <Coords points="647,574 668,574 668,584 647,584"/>
        </cell>
        <cell id="166" neighbors="155:R 162:L 165:T 167:B">
            <Coords points="647,589 668,589 668,599 647,599"/>
        </cell>
        <cell id="167" neighbors="163:L 166:T 168:R">
            <Coords points="646,613 668,613 668,623 646,623"/>
        </cell>
        <cell id="168" neighbors="105:T 156:R 167:L">
            <Coords points="683,613 703,613 703,622 683,622"/>
        </cell>
        <cell id="169" neighbors="119:T 140:R 175:L">
            <Coords points="361,613 393,613 393,623 361,623"/>
        </cell>
        <cell id="170" neighbors="171:R 182:T">
            <Coords points="55,604 101,604 101,621 55,621"/>
        </cell>
        <cell id="171" neighbors="170:L 172:R 208:T">
            <Coords points="129,612 175,612 175,623 129,623"/>
        </cell>
        <cell id="172" neighbors="171:L 173:R 214:T">
            <Coords points="185,613 217,613 217,623 185,623"/>
        </cell>
        <cell id="173" neighbors="172:L 174:R 192:T">
            <Coords points="225,613 257,613 257,623 225,623"/>
        </cell>
        <cell id="174" neighbors="173:L 175:R 193:T">
            <Coords points="275,613 294,613 294,622 275,622"/>
        </cell>
        <cell id="175" neighbors="169:R 174:L 201:T">
            <Coords points="304,613 351,613 351,621 304,621"/>
        </cell>
        <cell id="176" neighbors="21:T 177:B 183:R">
            <Coords points="55,423 118,423 118,453 55,453"/>
        </cell>
        <cell id="177" neighbors="176:T 178:B 202:R">
            <Coords points="56,459 101,459 101,467 56,467"/>
        </cell>
        <cell id="178" neighbors="177:T 179:B 203:R">
            <Coords points="56,474 113,474 113,499 56,499"/>
        </cell>
        <cell id="179" neighbors="178:T 180:B 205:R">
            <Coords points="56,519 105,519 105,540 56,540"/>
        </cell>
        <cell id="180" neighbors="179:T 181:B 206:R">
            <Coords points="56,545 100,545 100,555 56,555"/>
        </cell>
        <cell id="181" neighbors="180:T 182:B 207:R">
            <Coords points="56,560 112,560 112,584 56,584"/>
        </cell>
        <cell id="182" neighbors="170:B 181:T 208:R">
            <Coords points="57,590 100,590 100,597 57,597"/>
        </cell>
        <cell id="183" neighbors="27:T 176:L 184:R 202:B">
            <Coords points="138,442 175,442 175,453 138,453"/>
        </cell>
        <cell id="184" neighbors="29:T 183:L 185:R 209:B">
            <Coords points="185,442 217,442 217,452 185,452"/>
        </cell>
        <cell id="185" neighbors="30:T 184:L 186:R 216:B">
            <Coords points="239,443 259,443 259,451 239,451"/>
        </cell>
        <cell id="186" neighbors="46:T 185:L 187:B 194:R">
            <Coords points="287,442 295,442 295,451 287,451"/>
        </cell>
        <cell id="187" neighbors="186:T 188:B 196:R 217:L">
            <Coords points="288,489 295,489 295,499 288,499"/>
        </cell>
        <cell id="188" neighbors="187:T 193:B 198:R 212:L">
            <Coords points="288,529 294,529 294,537 288,537"/>
        </cell>
        <cell id="189" neighbors="190:B 197:R 211:L 217:T">
            <Coords points="251,506 256,506 256,514 251,514"/>
        </cell>
        <cell id="190" neighbors="189:T 191:L 199:R 215:B">
            <Coords points="250,543 257,543 257,553 250,553"/>
        </cell>
        <cell id="191" neighbors="190:R 206:L 212:T 213:B">
            <Coords points="209,545 218,545 218,553 209,553"/>
        </cell>
        <cell id="192" neighbors="173:B 201:R 214:L 215:T">
            <Coords points="249,590 257,590 257,599 249,599"/>
        </cell>
        <cell id="193" neighbors="174:B 188:T 200:R 215:L">
            <Coords points="288,574 294,574 294,583 288,583"/>
        </cell>
        <cell id="194" neighbors="35:T 112:R 186:L 195:B">
            <Coords points="313,442 351,442 351,451 313,451"/>
        </cell>
        <cell id="195" neighbors="113:R 194:T 196:B 216:L">
            <Coords points="313,458 349,458 349,468 313,468"/>
        </cell>
        <cell id="196" neighbors="114:R 187:L 195:T 197:B">
            <Coords points="311,490 350,490 350,500 311,500"/>
        </cell>
        <cell id="197" neighbors="115:R 189:L 196:T 198:B">
            <Coords points="314,506 350,506 350,515 314,515"/>
        </cell>
        <cell id="198" neighbors="116:R 188:L 197:T 199:B">
            <Coords points="318,529 350,529 350,539 318,539"/>
        </cell>
        <cell id="199" neighbors="117:R 190:L 198:T 200:B">
            <Coords points="333,545 349,545 349,553 333,553"/>
        </cell>
        <cell id="200" neighbors="118:R 193:L 199:T 201:B">
            <Coords points="319,574 350,574 350,583 319,583"/>
        </cell>
        <cell id="201" neighbors="119:R 175:B 192:L 200:T">
            <Coords points="324,590 351,590 351,599 324,599"/>
        </cell>
        <cell id="202" neighbors="177:L 183:T 203:B 209:R">
            <Coords points="137,457 177,457 177,467 137,467"/>
        </cell>
        <cell id="203" neighbors="178:L 202:T 204:B 210:R">
            <Coords points="137,490 176,490 176,500 137,500"/>
        </cell>
        <cell id="204" neighbors="203:T 205:B 211:R">
            <Coords points="138,506 176,506 176,515 138,515"/>
        </cell>
        <cell id="205" neighbors="179:L 204:T 206:B 212:R">
            <Coords points="143,529 175,529 175,538 143,538"/>
        </cell>
        <cell id="206" neighbors="180:L 191:R 205:T 207:B">
            <Coords points="158,544 175,544 175,553 158,553"/>
        </cell>
        <cell id="207" neighbors="181:L 206:T 208:B 213:R">
            <Coords points="143,575 174,575 174,584 143,584"/>
        </cell>
        <cell id="208" neighbors="171:B 182:L 207:T 214:R">
            <Coords points="150,590 175,590 175,600 150,600"/>
        </cell>
        <cell id="209" neighbors="184:T 202:L 210:B 216:R">
            <Coords points="191,458 217,458 217,466 191,466"/>
        </cell>
        <cell id="210" neighbors="203:L 209:T 211:B 217:R">
            <Coords points="185,491 217,491 217,500 185,500"/>
        </cell>
        <cell id="211" neighbors="189:R 204:L 210:T 212:B">
            <Coords points="192,505 216,505 216,515 192,515"/>
        </cell>
        <cell id="212" neighbors="188:R 191:B 205:L 211:T">
            <Coords points="190,529 218,529 218,539 190,539"/>
        </cell>
        <cell id="213" neighbors="191:T 207:L 214:B 215:R">
            <Coords points="189,574 217,574 217,583 189,583"/>
        </cell>
        <cell id="214" neighbors="172:B 192:R 208:L 213:T">
            <Coords points="198,590 217,590 217,599 198,599"/>
        </cell>
        <cell id="215" neighbors="190:T 192:B 193:R 213:L">
            <Coords points="239,573 257,573 257,583 239,583"/>
        </cell>
        <cell id="216" neighbors="185:T 195:R 209:L 217:B">
            <Coords points="240,459 257,459 257,466 240,466"/>
        </cell>
        <cell id="217" neighbors="187:R 189:B 210:L 216:T">
            <Coords points="239,489 256,489 256,499 239,499"/>
        </cell>
    </table>
    <table>
        <Coords points="53,729 53,944 736,944 736,729"/>
        <cell id="0" neighbors="1:B 6:T 10:R">
            <Coords points="56,831 172,831 172,850 56,850"/>
        </cell>
        <cell id="1" neighbors="0:T 2:B 11:R">
            <Coords points="56,857 99,857 99,865 56,865"/>
        </cell>
        <cell id="2" neighbors="1:T 3:B 12:R">
            <Coords points="57,869 171,869 171,879 57,879"/>
        </cell>
        <cell id="3" neighbors="2:T 4:B 13:R">
            <Coords points="56,883 187,883 187,891 56,891"/>
        </cell>
        <cell id="4" neighbors="3:T 5:B 14:R">
            <Coords points="56,896 187,896 187,915 56,915"/>
        </cell>
        <cell id="5" neighbors="4:T 28:R">
            <Coords points="56,921 187,921 187,941 56,941"/>
        </cell>
        <cell id="6" neighbors="0:B">
            <Coords points="54,751 92,751 92,763 54,763"/>
        </cell>
        <cell id="7" neighbors="15:B 30:R">
            <Coords points="236,766 335,766 335,775 236,775"/>
        </cell>
        <cell id="8" neighbors="9:B 15:R">
            <Coords points="219,803 252,803 252,812 219,812"/>
        </cell>
        <cell id="9" neighbors="8:T 10:B 18:R">
            <Coords points="239,817 252,817 252,825 239,825"/>
        </cell>
        <cell id="10" neighbors="0:L 9:T 11:B 19:R">
            <Coords points="221,841 252,841 252,850 221,850"/>
        </cell>
        <cell id="11" neighbors="1:L 10:T 12:B 20:R">
            <Coords points="222,856 254,856 254,865 222,865"/>
        </cell>
        <cell id="12" neighbors="2:L 11:T 13:B 25:R">
            <Coords points="222,869 252,869 252,878 222,878"/>
        </cell>
        <cell id="13" neighbors="3:L 12:T 14:B 26:R">
            <Coords points="227,883 253,883 253,891 227,891"/>
        </cell>
        <cell id="14" neighbors="4:L 13:T 28:B 54:R">
            <Coords points="235,905 253,905 253,914 235,914"/>
        </cell>
        <cell id="15" neighbors="7:T 8:L 16:R 18:B">
            <Coords points="271,779 312,779 312,811 271,811"/>
        </cell>
        <cell id="16" neighbors="15:L 17:B 32:R">
            <Coords points="331,780 372,780 372,812 331,812"/>
        </cell>
        <cell id="17" neighbors="16:T 18:L 21:B 33:R">
            <Coords points="358,816 371,816 371,827 358,827"/>
        </cell>
        <cell id="18" neighbors="9:L 15:T 17:R 19:B">
            <Coords points="298,816 312,816 312,827 298,827"/>
        </cell>
        <cell id="19" neighbors="10:L 18:T 20:B 21:R">
            <Coords points="286,840 314,840 314,850 286,850"/>
        </cell>
        <cell id="20" neighbors="11:L 19:T 22:R 25:B">
            <Coords points="288,855 314,855 314,865 288,865"/>
        </cell>
        <cell id="21" neighbors="17:T 19:L 22:B 44:R">
            <Coords points="348,841 374,841 374,850 348,850"/>
        </cell>
        <cell id="22" neighbors="20:L 21:T 23:B 45:R">
            <Coords points="349,856 373,856 373,864 349,864"/>
        </cell>
        <cell id="23" neighbors="22:T 24:B 25:L 46:R">
            <Coords points="356,870 372,870 372,878 356,878"/>
        </cell>
        <cell id="24" neighbors="23:T 26:L 29:B 47:R">
            <Coords points="361,883 373,883 373,891 361,891"/>
        </cell>
        <cell id="25" neighbors="12:L 20:T 23:R 26:B">
            <Coords points="297,870 313,870 313,878 297,878"/>
        </cell>
        <cell id="26" neighbors="13:L 24:R 25:T 27:B">
            <Coords points="301,884 315,884 315,891 301,891"/>
        </cell>
        <cell id="27" neighbors="26:T 28:L 29:R">
            <Coords points="301,931 313,931 313,940 301,940"/>
        </cell>
        <cell id="28" neighbors="5:L 14:T 27:R">
            <Coords points="227,932 258,932 258,940 227,940"/>
        </cell>
        <cell id="29" neighbors="24:T 27:L 55:R">
            <Coords points="361,931 373,931 373,940 361,940"/>
        </cell>
        <cell id="30" neighbors="7:L 31:B 39:R">
            <Coords points="427,766 504,766 504,773 427,773"/>
        </cell>
        <cell id="31" neighbors="30:T 32:L 34:B 42:R">
            <Coords points="452,779 492,779 492,812 452,812"/>
        </cell>
        <cell id="32" neighbors="16:L 31:R 33:B">
            <Coords points="398,804 432,804 432,812 398,812"/>
        </cell>
        <cell id="33" neighbors="17:L 32:T 34:R 44:B">
            <Coords points="418,817 434,817 434,825 418,825"/>
        </cell>
        <cell id="34" neighbors="31:T 33:L 35:R 48:B">
            <Coords points="477,816 491,816 491,825 477,825"/>
        </cell>
        <cell id="35" neighbors="34:L 36:R 42:T 51:B">
            <Coords points="538,817 552,817 552,827 538,827"/>
        </cell>
        <cell id="36" neighbors="35:L 37:R 43:T 58:B">
            <Coords points="602,817 613,817 613,826 602,826"/>
        </cell>
        <cell id="37" neighbors="36:L 38:R 40:T 62:B">
            <Coords points="663,816 673,816 673,827 663,827"/>
        </cell>
        <cell id="38" neighbors="37:L 41:T 65:B">
            <Coords points="724,817 732,817 732,826 724,826"/>
        </cell>
        <cell id="39" neighbors="30:L 40:B">
            <Coords points="612,765 679,765 679,775 612,775"/>
        </cell>
        <cell id="40" neighbors="37:B 39:T 41:R 43:L">
            <Coords points="631,778 672,778 672,812 631,812"/>
        </cell>
        <cell id="41" neighbors="38:B 40:L">
            <Coords points="690,779 731,779 731,812 690,812"/>
        </cell>
        <cell id="42" neighbors="31:L 35:B 43:R">
            <Coords points="510,778 552,778 552,811 510,811"/>
        </cell>
        <cell id="43" neighbors="36:B 40:R 42:L">
            <Coords points="578,802 611,802 611,812 578,812"/>
        </cell>
        <cell id="44" neighbors="21:L 33:T 45:B 48:R">
            <Coords points="404,841 435,841 435,850 404,850"/>
        </cell>
        <cell id="45" neighbors="22:L 44:T 46:B 49:R">
            <Coords points="403,855 436,855 436,866 403,866"/>
        </cell>
        <cell id="46" neighbors="23:L 45:T 47:B 50:R">
            <Coords points="413,869 436,869 436,881 413,881"/>
        </cell>
        <cell id="47" neighbors="24:L 46:T 54:B 61:R">
            <Coords points="418,882 435,882 435,893 418,893"/>
        </cell>
        <cell id="48" neighbors="34:T 44:L 49:B 51:R">
            <Coords points="472,841 496,841 496,851 472,851"/>
        </cell>
        <cell id="49" neighbors="45:L 48:T 50:B 52:R">
            <Coords points="472,855 496,855 496,866 472,866"/>
        </cell>
        <cell id="50" neighbors="46:L 49:T 53:R">
            <Coords points="478,869 496,869 496,880 478,880"/>
        </cell>
        <cell id="51" neighbors="35:T 48:L 52:B 58:R">
            <Coords points="532,841 556,841 556,850 532,850"/>
        </cell>
        <cell id="52" neighbors="49:L 51:T 53:B 59:R">
            <Coords points="533,855 555,855 555,866 533,866"/>
        </cell>
        <cell id="53" neighbors="50:L 52:T 60:R">
            <Coords points="538,870 556,870 556,879 538,879"/>
        </cell>
        <cell id="54" neighbors="14:L 47:T 55:B 56:R">
            <Coords points="424,907 436,907 436,915 424,915"/>
        </cell>
        <cell id="55" neighbors="29:L 54:T 57:R">
            <Coords points="423,932 436,932 436,941 423,941"/>
        </cell>
        <cell id="56" neighbors="54:L 57:B 61:T">
            <Coords points="597,906 613,906 613,914 597,914"/>
        </cell>
        <cell id="57" neighbors="55:L 56:T">
            <Coords points="598,932 614,932 614,939 598,939"/>
        </cell>
        <cell id="58" neighbors="36:T 51:L 59:B 62:R">
            <Coords points="598,842 614,842 614,849 598,849"/>
        </cell>
        <cell id="59" neighbors="52:L 58:T 60:B 63:R">
            <Coords points="598,855 613,855 613,865 598,865"/>
        </cell>
        <cell id="60" neighbors="53:L 59:T 61:B 64:R">
            <Coords points="599,869 613,869 613,878 599,878"/>
        </cell>
        <cell id="61" neighbors="47:L 56:B 60:T">
            <Coords points="599,883 614,883 614,891 599,891"/>
        </cell>
        <cell id="62" neighbors="37:T 58:L 63:B 65:R">
            <Coords points="658,840 673,840 673,849 658,849"/>
        </cell>
        <cell id="63" neighbors="59:L 62:T 64:B 66:R">
            <Coords points="658,856 672,856 672,865 658,865"/>
        </cell>
        <cell id="64" neighbors="60:L 63:T 67:R">
            <Coords points="657,869 673,869 673,878 657,878"/>
        </cell>
        <cell id="65" neighbors="38:T 62:L 66:B">
            <Coords points="714,841 732,841 732,849 714,849"/>
        </cell>
        <cell id="66" neighbors="63:L 65:T 67:B">
            <Coords points="713,855 733,855 733,865 713,865"/>
        </cell>
        <cell id="67" neighbors="64:L 66:T">
            <Coords points="718,869 735,869 735,878 718,878"/>
        </cell>
    </table>
</document>
