<?xml version="1.0" encoding="UTF-8"?>
<document filename="cTDaR_t10189.jpg">
    <table>
        <Coords points="68,168 68,286 749,286 749,168"/>
        <cell id="0" neighbors="1:L 3:B">
            <Coords points="691,166 716,166 716,178 691,178"/>
        </cell>
        <cell id="1" neighbors="0:R 2:B">
            <Coords points="591,167 617,167 617,178 591,178"/>
        </cell>
        <cell id="2" neighbors="1:T 3:R 4:B 14:L">
            <Coords points="560,183 647,183 647,195 560,195"/>
        </cell>
        <cell id="3" neighbors="0:T 2:L 6:B">
            <Coords points="659,182 745,182 745,196 659,196"/>
        </cell>
        <cell id="4" neighbors="2:T 5:B 6:R 15:L">
            <Coords points="609,200 648,200 648,213 609,213"/>
        </cell>
        <cell id="5" neighbors="4:T 7:R 9:B 16:L">
            <Coords points="615,218 648,218 648,229 615,229"/>
        </cell>
        <cell id="6" neighbors="3:T 4:L 7:B">
            <Coords points="708,200 746,200 746,212 708,212"/>
        </cell>
        <cell id="7" neighbors="5:L 6:T 8:B">
            <Coords points="715,217 745,217 745,230 715,230"/>
        </cell>
        <cell id="8" neighbors="7:T 9:L 11:B">
            <Coords points="708,235 745,235 745,247 708,247"/>
        </cell>
        <cell id="9" neighbors="5:T 8:R 10:B 17:L">
            <Coords points="609,235 647,235 647,247 609,247"/>
        </cell>
        <cell id="10" neighbors="9:T 11:R 12:B 18:L">
            <Coords points="605,252 652,252 652,266 605,266"/>
        </cell>
        <cell id="11" neighbors="8:T 10:L 13:B">
            <Coords points="704,251 750,251 750,265 704,265"/>
        </cell>
        <cell id="12" neighbors="10:T 13:R 19:L">
            <Coords points="560,269 648,269 648,281 560,281"/>
        </cell>
        <cell id="13" neighbors="11:T 12:L">
            <Coords points="659,269 745,269 745,282 659,282"/>
        </cell>
        <cell id="14" neighbors="2:R 15:B">
            <Coords points="69,181 174,181 174,196 69,196"/>
        </cell>
        <cell id="15" neighbors="4:R 14:T 16:B">
            <Coords points="69,198 328,198 328,214 69,214"/>
        </cell>
        <cell id="16" neighbors="5:R 15:T 17:B">
            <Coords points="69,217 208,217 208,231 69,231"/>
        </cell>
        <cell id="17" neighbors="9:R 16:T 18:B">
            <Coords points="94,233 291,233 291,248 94,248"/>
        </cell>
        <cell id="18" neighbors="10:R 17:T 19:B">
            <Coords points="69,252 301,252 301,265 69,265"/>
        </cell>
        <cell id="19" neighbors="12:R 18:T">
            <Coords points="92,268 309,268 309,283 92,283"/>
        </cell>
    </table>
    <table>
        <Coords points="68,340 68,406 749,406 749,340"/>
        <cell id="0" neighbors="1:R 2:B">
            <Coords points="592,339 617,339 617,349 592,349"/>
        </cell>
        <cell id="1" neighbors="0:L 3:B">
            <Coords points="690,338 715,338 715,349 690,349"/>
        </cell>
        <cell id="2" neighbors="0:T 3:R 7:B 8:L">
            <Coords points="560,354 646,354 646,366 560,366"/>
        </cell>
        <cell id="3" neighbors="1:T 2:L 4:B">
            <Coords points="658,354 746,354 746,366 658,366"/>
        </cell>
        <cell id="4" neighbors="3:T 5:B 7:L">
            <Coords points="714,371 745,371 745,384 714,384"/>
        </cell>
        <cell id="5" neighbors="4:T 6:L">
            <Coords points="660,389 746,389 746,402 660,402"/>
        </cell>
        <cell id="6" neighbors="5:R 7:T 10:L">
            <Coords points="559,389 646,389 646,401 559,401"/>
        </cell>
        <cell id="7" neighbors="2:T 4:R 6:B 9:L">
            <Coords points="610,372 647,372 647,384 610,384"/>
        </cell>
        <cell id="8" neighbors="2:R 9:B">
            <Coords points="70,354 186,354 186,368 70,368"/>
        </cell>
        <cell id="9" neighbors="7:R 8:T 10:B">
            <Coords points="70,371 215,371 215,386 70,386"/>
        </cell>
        <cell id="10" neighbors="6:R 9:T">
            <Coords points="93,388 266,388 266,402 93,402"/>
        </cell>
    </table>
    <table>
        <Coords points="68,481 68,565 749,565 749,481"/>
        <cell id="0" neighbors="1:L 2:R 4:B">
            <Coords points="598,480 623,480 623,491 598,491"/>
        </cell>
        <cell id="1" neighbors="0:R 3:B">
            <Coords points="504,479 529,479 529,491 504,491"/>
        </cell>
        <cell id="2" neighbors="0:L 5:B">
            <Coords points="692,480 717,480 717,491 692,491"/>
        </cell>
        <cell id="3" neighbors="1:T 4:R 6:B 15:L">
            <Coords points="475,496 558,496 558,509 475,509"/>
        </cell>
        <cell id="4" neighbors="0:T 3:L 5:R 10:B">
            <Coords points="570,496 649,496 649,509 570,509"/>
        </cell>
        <cell id="5" neighbors="2:T 4:L 12:B">
            <Coords points="662,496 746,496 746,509 662,509"/>
        </cell>
        <cell id="6" neighbors="3:T 7:B 10:R 16:L">
            <Coords points="523,514 561,514 561,527 523,527"/>
        </cell>
        <cell id="7" neighbors="6:T 8:B 11:R 17:L">
            <Coords points="523,531 561,531 561,545 523,545"/>
        </cell>
        <cell id="8" neighbors="7:T 9:R 18:L">
            <Coords points="475,549 557,549 557,560 475,560"/>
        </cell>
        <cell id="9" neighbors="8:L 11:T 14:R">
            <Coords points="568,549 651,549 651,560 568,560"/>
        </cell>
        <cell id="10" neighbors="4:T 6:L 11:B 12:R">
            <Coords points="626,514 656,514 656,527 626,527"/>
        </cell>
        <cell id="11" neighbors="7:L 9:B 10:T 13:R">
            <Coords points="626,531 655,531 655,545 626,545"/>
        </cell>
        <cell id="12" neighbors="5:T 10:L 13:B">
            <Coords points="721,514 750,514 750,527 721,527"/>
        </cell>
        <cell id="13" neighbors="11:L 12:T 14:B">
            <Coords points="721,531 749,531 749,544 721,544"/>
        </cell>
        <cell id="14" neighbors="9:L 13:T">
            <Coords points="663,549 746,549 746,560 663,560"/>
        </cell>
        <cell id="15" neighbors="3:R 16:B">
            <Coords points="69,496 225,496 225,509 69,509"/>
        </cell>
        <cell id="16" neighbors="6:R 15:T 17:B">
            <Coords points="70,514 161,514 161,527 70,527"/>
        </cell>
        <cell id="17" neighbors="7:R 16:T 18:B">
            <Coords points="70,530 174,530 174,545 70,545"/>
        </cell>
        <cell id="18" neighbors="8:R 17:T">
            <Coords points="94,547 276,547 276,562 94,562"/>
        </cell>
    </table>
    <table>
        <Coords points="68,670 68,814 749,814 749,670"/>
        <cell id="0" neighbors="1:L 6:B">
            <Coords points="621,669 646,669 646,680 621,680"/>
        </cell>
        <cell id="1" neighbors="0:R 3:B">
            <Coords points="382,668 407,668 407,680 382,680"/>
        </cell>
        <cell id="2" neighbors="3:R 8:B">
            <Coords points="290,690 336,690 336,722 290,722"/>
        </cell>
        <cell id="3" neighbors="1:T 2:L 4:R 9:B">
            <Coords points="359,700 428,700 428,722 359,722"/>
        </cell>
        <cell id="4" neighbors="3:L 5:R 10:B">
            <Coords points="452,690 497,690 497,722 452,722"/>
        </cell>
        <cell id="5" neighbors="4:L 6:R 11:B">
            <Coords points="529,690 575,690 575,722 529,722"/>
        </cell>
        <cell id="6" neighbors="0:T 5:L 7:R 12:B">
            <Coords points="599,701 667,701 667,722 599,722"/>
        </cell>
        <cell id="7" neighbors="6:L 13:B">
            <Coords points="690,689 736,689 736,721 690,721"/>
        </cell>
        <cell id="8" neighbors="2:T 9:R 15:B 24:L">
            <Coords points="280,744 346,744 346,757 280,757"/>
        </cell>
        <cell id="9" neighbors="3:T 8:L 10:R 19:B">
            <Coords points="358,743 434,743 434,757 358,757"/>
        </cell>
        <cell id="10" neighbors="4:T 9:L 11:R 16:B">
            <Coords points="442,743 507,743 507,755 442,755"/>
        </cell>
        <cell id="11" neighbors="5:T 10:L 12:R 17:B">
            <Coords points="519,743 584,743 584,756 519,756"/>
        </cell>
        <cell id="12" neighbors="6:T 11:L 13:R 22:B">
            <Coords points="597,743 673,743 673,756 597,756"/>
        </cell>
        <cell id="13" neighbors="7:T 12:L 14:B">
            <Coords points="681,743 746,743 746,756 681,756"/>
        </cell>
        <cell id="14" neighbors="13:T 17:L 23:B">
            <Coords points="726,778 746,778 746,788 726,788"/>
        </cell>
        <cell id="15" neighbors="8:T 16:R 18:B 25:L">
            <Coords points="325,777 346,777 346,788 325,788"/>
        </cell>
        <cell id="16" neighbors="10:T 15:L 17:R 20:B">
            <Coords points="487,776 507,776 507,788 487,788"/>
        </cell>
        <cell id="17" neighbors="11:T 14:R 16:L 21:B">
            <Coords points="564,777 585,777 585,788 564,788"/>
        </cell>
        <cell id="18" neighbors="15:T 19:R 26:L">
            <Coords points="280,795 346,795 346,808 280,808"/>
        </cell>
        <cell id="19" neighbors="9:T 18:L 20:R">
            <Coords points="358,795 434,795 434,808 358,808"/>
        </cell>
        <cell id="20" neighbors="16:T 19:L 21:R">
            <Coords points="442,795 508,795 508,807 442,807"/>
        </cell>
        <cell id="21" neighbors="17:T 20:L 22:R">
            <Coords points="519,795 585,795 585,808 519,808"/>
        </cell>
        <cell id="22" neighbors="12:T 21:L 23:R">
            <Coords points="596,795 672,795 672,808 596,808"/>
        </cell>
        <cell id="23" neighbors="14:T 22:L">
            <Coords points="680,794 746,794 746,808 680,808"/>
        </cell>
        <cell id="24" neighbors="8:R 25:B">
            <Coords points="69,729 230,729 230,757 69,757"/>
        </cell>
        <cell id="25" neighbors="15:R 24:T 26:B">
            <Coords points="70,762 262,762 262,791 70,791"/>
        </cell>
        <cell id="26" neighbors="18:R 25:T">
            <Coords points="93,795 264,795 264,809 93,809"/>
        </cell>
    </table>
</document>
