<?xml version="1.0" encoding="UTF-8"?>
<document filename="cTDaR_t10039.jpg">
    <table>
        <Coords points="71,164 71,953 744,953 744,164"/>
        <cell id="0" neighbors="1:B 2:B">
            <Coords points="456,166 542,166 542,178 456,178"/>
        </cell>
        <cell id="1" neighbors="0:T 2:R 12:B 14:L">
            <Coords points="466,180 491,180 491,191 466,191"/>
        </cell>
        <cell id="2" neighbors="0:T 1:L 3:R 11:B">
            <Coords points="515,181 539,181 539,191 515,191"/>
        </cell>
        <cell id="3" neighbors="2:L 4:R 10:B">
            <Coords points="563,180 589,180 589,191 563,191"/>
        </cell>
        <cell id="4" neighbors="3:L 5:R 7:B">
            <Coords points="613,181 636,181 636,191 613,191"/>
        </cell>
        <cell id="5" neighbors="4:L 6:R 8:B">
            <Coords points="660,181 684,181 684,191 660,191"/>
        </cell>
        <cell id="6" neighbors="5:L 9:B">
            <Coords points="707,181 731,181 731,191 707,191"/>
        </cell>
        <cell id="7" neighbors="4:T 8:R 10:L 23:B">
            <Coords points="614,196 641,196 641,206 614,206"/>
        </cell>
        <cell id="8" neighbors="5:T 7:L 9:R 22:B">
            <Coords points="663,196 688,196 688,206 663,206"/>
        </cell>
        <cell id="9" neighbors="6:T 8:L 21:B">
            <Coords points="711,196 737,196 737,207 711,207"/>
        </cell>
        <cell id="10" neighbors="3:T 7:R 11:L 24:B">
            <Coords points="567,196 593,196 593,206 567,206"/>
        </cell>
        <cell id="11" neighbors="2:T 10:R 12:L 25:B">
            <Coords points="519,195 545,195 545,205 519,205"/>
        </cell>
        <cell id="12" neighbors="1:T 11:R 13:L 26:B">
            <Coords points="469,194 496,194 496,205 469,205"/>
        </cell>
        <cell id="13" neighbors="12:R 14:T 16:L 27:B">
            <Coords points="421,195 447,195 447,205 421,205"/>
        </cell>
        <cell id="14" neighbors="1:R 13:B 15:L">
            <Coords points="417,180 441,180 441,191 417,191"/>
        </cell>
        <cell id="15" neighbors="14:R 16:B 18:L">
            <Coords points="370,180 393,180 393,191 370,191"/>
        </cell>
        <cell id="16" neighbors="13:R 15:T 17:L 28:B">
            <Coords points="373,194 398,194 398,205 373,205"/>
        </cell>
        <cell id="17" neighbors="16:R 18:T 20:L 29:B">
            <Coords points="332,195 349,195 349,204 332,204"/>
        </cell>
        <cell id="18" neighbors="15:R 17:B 19:L">
            <Coords points="320,180 344,180 344,190 320,190"/>
        </cell>
        <cell id="19" neighbors="18:R 20:B">
            <Coords points="270,180 294,180 294,191 270,191"/>
        </cell>
        <cell id="20" neighbors="17:R 19:T 33:B 35:L">
            <Coords points="281,194 300,194 300,204 281,204"/>
        </cell>
        <cell id="21" neighbors="9:T 22:L 92:B">
            <Coords points="711,243 737,243 737,253 711,253"/>
        </cell>
        <cell id="22" neighbors="8:T 21:R 23:L 103:B">
            <Coords points="662,243 688,243 688,253 662,253"/>
        </cell>
        <cell id="23" neighbors="7:T 22:R 24:L 104:B">
            <Coords points="614,243 641,243 641,253 614,253"/>
        </cell>
        <cell id="24" neighbors="10:T 23:R 25:L 121:B">
            <Coords points="567,244 595,244 595,253 567,253"/>
        </cell>
        <cell id="25" neighbors="11:T 24:R 26:L 30:B">
            <Coords points="518,242 545,242 545,252 518,252"/>
        </cell>
        <cell id="26" neighbors="12:T 25:R 27:L 31:B">
            <Coords points="469,241 496,241 496,252 469,252"/>
        </cell>
        <cell id="27" neighbors="13:T 26:R 28:L 32:B">
            <Coords points="421,241 447,241 447,252 421,252"/>
        </cell>
        <cell id="28" neighbors="16:T 27:R 29:L 46:B">
            <Coords points="372,241 398,241 398,251 372,251"/>
        </cell>
        <cell id="29" neighbors="17:T 28:R 33:L 45:B">
            <Coords points="323,241 349,241 349,252 323,252"/>
        </cell>
        <cell id="30" neighbors="25:T 31:L 49:B">
            <Coords points="528,258 545,258 545,267 528,267"/>
        </cell>
        <cell id="31" neighbors="26:T 30:R 32:L 48:B">
            <Coords points="480,257 496,257 496,267 480,267"/>
        </cell>
        <cell id="32" neighbors="27:T 31:R 39:L 47:B">
            <Coords points="434,258 448,258 448,267 434,267"/>
        </cell>
        <cell id="33" neighbors="20:T 29:R 38:L 44:B">
            <Coords points="274,241 299,241 299,252 274,252"/>
        </cell>
        <cell id="34" neighbors="">
            <Coords points="144,173 186,173 186,184 144,184"/>
        </cell>
        <cell id="35" neighbors="20:R 36:B">
            <Coords points="79,194 146,194 146,205 79,205"/>
        </cell>
        <cell id="36" neighbors="35:T 37:B">
            <Coords points="91,209 175,209 175,222 91,222"/>
        </cell>
        <cell id="37" neighbors="36:T 38:B">
            <Coords points="78,226 164,226 164,236 78,236"/>
        </cell>
        <cell id="38" neighbors="33:R 37:T 39:B">
            <Coords points="90,241 237,241 237,254 90,254"/>
        </cell>
        <cell id="39" neighbors="32:R 38:T 40:B">
            <Coords points="91,256 157,256 157,267 91,267"/>
        </cell>
        <cell id="40" neighbors="39:T 41:B">
            <Coords points="91,273 229,273 229,284 91,284"/>
        </cell>
        <cell id="41" neighbors="40:T 42:B 44:R">
            <Coords points="104,289 198,289 198,300 104,300"/>
        </cell>
        <cell id="42" neighbors="41:T 43:B 47:R">
            <Coords points="103,304 141,304 141,314 103,314"/>
        </cell>
        <cell id="43" neighbors="42:T 50:R 86:B">
            <Coords points="103,319 161,319 161,332 103,332"/>
        </cell>
        <cell id="44" neighbors="33:T 41:L 45:R 58:B">
            <Coords points="281,289 301,289 301,298 281,298"/>
        </cell>
        <cell id="45" neighbors="29:T 44:L 46:R 57:B">
            <Coords points="332,288 350,288 350,299 332,299"/>
        </cell>
        <cell id="46" neighbors="28:T 45:L 56:B">
            <Coords points="381,289 398,289 398,298 381,298"/>
        </cell>
        <cell id="47" neighbors="32:T 42:L 48:R 50:B">
            <Coords points="430,305 447,305 447,314 430,314"/>
        </cell>
        <cell id="48" neighbors="31:T 47:L 49:R 51:B">
            <Coords points="478,305 496,305 496,314 478,314"/>
        </cell>
        <cell id="49" neighbors="30:T 48:L 52:B">
            <Coords points="526,304 545,304 545,314 526,314"/>
        </cell>
        <cell id="50" neighbors="43:L 47:T 51:R 53:B">
            <Coords points="429,321 447,321 447,330 429,330"/>
        </cell>
        <cell id="51" neighbors="48:T 50:L 52:R 54:B">
            <Coords points="478,321 496,321 496,331 478,331"/>
        </cell>
        <cell id="52" neighbors="49:T 51:L 55:B">
            <Coords points="527,320 545,320 545,330 527,330"/>
        </cell>
        <cell id="53" neighbors="50:T 54:R 56:L 69:B">
            <Coords points="422,336 448,336 448,346 422,346"/>
        </cell>
        <cell id="54" neighbors="51:T 53:L 55:R 68:B">
            <Coords points="470,336 495,336 495,346 470,346"/>
        </cell>
        <cell id="55" neighbors="52:T 54:L 59:B">
            <Coords points="519,336 545,336 545,346 519,346"/>
        </cell>
        <cell id="56" neighbors="46:T 53:R 57:L 74:B">
            <Coords points="381,336 398,336 398,345 381,345"/>
        </cell>
        <cell id="57" neighbors="45:T 56:R 58:L 78:B">
            <Coords points="332,336 349,336 349,345 332,345"/>
        </cell>
        <cell id="58" neighbors="44:T 57:R 85:B 86:L">
            <Coords points="281,335 299,335 299,346 281,346"/>
        </cell>
        <cell id="59" neighbors="55:T 60:B 68:L">
            <Coords points="519,351 545,351 545,361 519,361"/>
        </cell>
        <cell id="60" neighbors="59:T 61:B 67:L">
            <Coords points="520,368 545,368 545,378 520,378"/>
        </cell>
        <cell id="61" neighbors="60:T 62:B 66:L">
            <Coords points="524,384 545,384 545,394 524,394"/>
        </cell>
        <cell id="62" neighbors="61:T 63:B 65:L">
            <Coords points="524,399 544,399 544,410 524,410"/>
        </cell>
        <cell id="63" neighbors="62:T 64:L 135:B">
            <Coords points="523,415 544,415 544,425 523,425"/>
        </cell>
        <cell id="64" neighbors="63:R 65:T 73:L 136:B">
            <Coords points="475,415 496,415 496,425 475,425"/>
        </cell>
        <cell id="65" neighbors="62:R 64:B 66:T 72:L">
            <Coords points="475,399 496,399 496,410 475,410"/>
        </cell>
        <cell id="66" neighbors="61:R 65:B 67:T 71:L">
            <Coords points="475,384 496,384 496,393 475,393"/>
        </cell>
        <cell id="67" neighbors="60:R 66:B 68:T 70:L">
            <Coords points="478,368 496,368 496,378 478,378"/>
        </cell>
        <cell id="68" neighbors="54:T 59:R 67:B 69:L">
            <Coords points="471,351 495,351 495,362 471,362"/>
        </cell>
        <cell id="69" neighbors="53:T 68:R 70:B 87:L">
            <Coords points="429,351 447,351 447,361 429,361"/>
        </cell>
        <cell id="70" neighbors="67:R 69:T 71:B 74:L">
            <Coords points="429,368 448,368 448,377 429,377"/>
        </cell>
        <cell id="71" neighbors="66:R 70:T 72:B 75:L">
            <Coords points="425,384 447,384 447,393 425,393"/>
        </cell>
        <cell id="72" neighbors="65:R 71:T 73:B 76:L">
            <Coords points="425,399 447,399 447,409 425,409"/>
        </cell>
        <cell id="73" neighbors="64:R 72:T 77:L 151:B">
            <Coords points="426,415 447,415 447,426 426,426"/>
        </cell>
        <cell id="74" neighbors="56:T 70:R 75:B 78:L">
            <Coords points="381,368 398,368 398,378 381,378"/>
        </cell>
        <cell id="75" neighbors="71:R 74:T 76:B 79:L">
            <Coords points="377,384 398,384 398,394 377,394"/>
        </cell>
        <cell id="76" neighbors="72:R 75:T 77:B 80:L">
            <Coords points="377,398 397,398 397,409 377,409"/>
        </cell>
        <cell id="77" neighbors="73:R 76:T 81:L 152:B">
            <Coords points="377,414 398,414 398,425 377,425"/>
        </cell>
        <cell id="78" neighbors="57:T 74:R 79:B 85:L">
            <Coords points="332,368 349,368 349,378 332,378"/>
        </cell>
        <cell id="79" neighbors="75:R 78:T 80:B 84:L">
            <Coords points="328,384 349,384 349,394 328,394"/>
        </cell>
        <cell id="80" neighbors="76:R 79:T 81:B 83:L">
            <Coords points="328,398 349,398 349,410 328,410"/>
        </cell>
        <cell id="81" neighbors="77:R 80:T 82:L 154:B">
            <Coords points="332,415 349,415 349,424 332,424"/>
        </cell>
        <cell id="82" neighbors="81:R 83:T 91:L 155:B">
            <Coords points="287,415 298,415 298,425 287,425"/>
        </cell>
        <cell id="83" neighbors="80:R 82:B 84:T 90:L">
            <Coords points="279,399 299,399 299,409 279,409"/>
        </cell>
        <cell id="84" neighbors="79:R 83:B 85:T 89:L">
            <Coords points="279,384 299,384 299,394 279,394"/>
        </cell>
        <cell id="85" neighbors="58:T 78:R 84:B 88:L">
            <Coords points="282,368 300,368 300,377 282,377"/>
        </cell>
        <cell id="86" neighbors="43:T 58:R 87:B">
            <Coords points="103,335 202,335 202,347 103,347"/>
        </cell>
        <cell id="87" neighbors="69:R 86:T 88:B">
            <Coords points="102,351 170,351 170,362 102,362"/>
        </cell>
        <cell id="88" neighbors="85:R 87:T 89:B">
            <Coords points="103,368 226,368 226,380 103,380"/>
        </cell>
        <cell id="89" neighbors="84:R 88:T 90:B">
            <Coords points="103,383 211,383 211,394 103,394"/>
        </cell>
        <cell id="90" neighbors="83:R 89:T 91:B">
            <Coords points="103,399 201,399 201,410 103,410"/>
        </cell>
        <cell id="91" neighbors="82:R 90:T 173:B">
            <Coords points="103,415 221,415 221,426 103,426"/>
        </cell>
        <cell id="92" neighbors="21:T 93:B 103:L">
            <Coords points="711,445 737,445 737,454 711,454"/>
        </cell>
        <cell id="93" neighbors="92:T 94:B 102:L">
            <Coords points="715,460 737,460 737,472 715,472"/>
        </cell>
        <cell id="94" neighbors="93:T 95:B 101:L">
            <Coords points="715,475 736,475 736,487 715,487"/>
        </cell>
        <cell id="95" neighbors="94:T 96:B 100:L">
            <Coords points="715,491 737,491 737,502 715,502"/>
        </cell>
        <cell id="96" neighbors="95:T 97:B 99:L">
            <Coords points="712,507 737,507 737,517 712,517"/>
        </cell>
        <cell id="97" neighbors="96:T 98:L 112:B">
            <Coords points="719,522 737,522 737,533 719,533"/>
        </cell>
        <cell id="98" neighbors="97:R 99:T 109:L 111:B">
            <Coords points="669,523 689,523 689,532 669,532"/>
        </cell>
        <cell id="99" neighbors="96:R 98:B 100:T 108:L">
            <Coords points="662,507 689,507 689,518 662,518"/>
        </cell>
        <cell id="100" neighbors="95:R 99:B 101:T 107:L">
            <Coords points="667,491 687,491 687,502 667,502"/>
        </cell>
        <cell id="101" neighbors="94:R 100:B 102:T 106:L">
            <Coords points="666,475 688,475 688,487 666,487"/>
        </cell>
        <cell id="102" neighbors="93:R 101:B 103:T 105:L">
            <Coords points="667,460 687,460 687,472 667,472"/>
        </cell>
        <cell id="103" neighbors="22:T 92:R 102:B 104:L">
            <Coords points="662,444 688,444 688,455 662,455"/>
        </cell>
        <cell id="104" neighbors="23:T 103:R 105:B 121:L">
            <Coords points="614,444 641,444 641,455 614,455"/>
        </cell>
        <cell id="105" neighbors="102:R 104:T 106:B 122:L">
            <Coords points="620,460 640,460 640,472 620,472"/>
        </cell>
        <cell id="106" neighbors="101:R 105:T 107:B 123:L">
            <Coords points="618,475 640,475 640,487 618,487"/>
        </cell>
        <cell id="107" neighbors="100:R 106:T 108:B 124:L">
            <Coords points="619,491 639,491 639,504 619,504"/>
        </cell>
        <cell id="108" neighbors="99:R 107:T 109:B 125:L">
            <Coords points="615,508 641,508 641,518 615,518"/>
        </cell>
        <cell id="109" neighbors="98:R 108:T 110:B 126:L">
            <Coords points="622,522 640,522 640,533 622,533"/>
        </cell>
        <cell id="110" neighbors="109:T 111:R 115:B 127:L">
            <Coords points="623,539 641,539 641,549 623,549"/>
        </cell>
        <cell id="111" neighbors="98:T 110:L 112:R 114:B">
            <Coords points="671,539 688,539 688,549 671,549"/>
        </cell>
        <cell id="112" neighbors="97:T 111:L 113:B">
            <Coords points="720,539 736,539 736,549 720,549"/>
        </cell>
        <cell id="113" neighbors="112:T 114:L 120:B">
            <Coords points="706,555 737,555 737,564 706,564"/>
        </cell>
        <cell id="114" neighbors="111:T 113:R 115:L 119:B">
            <Coords points="658,555 689,555 689,564 658,564"/>
        </cell>
        <cell id="115" neighbors="110:T 114:R 116:L 118:B">
            <Coords points="609,555 642,555 642,564 609,564"/>
        </cell>
        <cell id="116" neighbors="115:R 117:B 127:T 129:L">
            <Coords points="561,555 593,555 593,564 561,564"/>
        </cell>
        <cell id="117" neighbors="116:T 118:R 128:L 189:B">
            <Coords points="561,570 594,570 594,580 561,580"/>
        </cell>
        <cell id="118" neighbors="115:T 117:L 119:R 190:B">
            <Coords points="609,569 641,569 641,580 609,580"/>
        </cell>
        <cell id="119" neighbors="114:T 118:L 120:R 195:B">
            <Coords points="658,570 688,570 688,581 658,581"/>
        </cell>
        <cell id="120" neighbors="113:T 119:L 196:B">
            <Coords points="706,570 737,570 737,580 706,580"/>
        </cell>
        <cell id="121" neighbors="24:T 104:R 122:B 173:L">
            <Coords points="561,444 593,444 593,455 561,455"/>
        </cell>
        <cell id="122" neighbors="105:R 121:T 123:B 135:L">
            <Coords points="571,461 592,461 592,471 571,471"/>
        </cell>
        <cell id="123" neighbors="106:R 122:T 124:B 134:L">
            <Coords points="571,475 591,475 591,488 571,488"/>
        </cell>
        <cell id="124" neighbors="107:R 123:T 125:B 133:L">
            <Coords points="571,492 592,492 592,503 571,503"/>
        </cell>
        <cell id="125" neighbors="108:R 124:T 126:B 132:L">
            <Coords points="567,507 593,507 593,517 567,517"/>
        </cell>
        <cell id="126" neighbors="109:R 125:T 127:B 131:L">
            <Coords points="575,523 593,523 593,533 575,533"/>
        </cell>
        <cell id="127" neighbors="110:R 116:B 126:T 130:L">
            <Coords points="572,538 593,538 593,550 572,550"/>
        </cell>
        <cell id="128" neighbors="117:R 129:T 143:L 188:B">
            <Coords points="514,568 546,568 546,579 514,579"/>
        </cell>
        <cell id="129" neighbors="116:R 128:B 130:T 142:L">
            <Coords points="515,553 545,553 545,564 515,564"/>
        </cell>
        <cell id="130" neighbors="127:R 129:B 131:T 141:L">
            <Coords points="523,538 545,538 545,549 523,549"/>
        </cell>
        <cell id="131" neighbors="126:R 130:B 132:T 140:L">
            <Coords points="528,521 546,521 546,531 528,531"/>
        </cell>
        <cell id="132" neighbors="125:R 131:B 133:T 139:L">
            <Coords points="519,506 544,506 544,516 519,516"/>
        </cell>
        <cell id="133" neighbors="124:R 132:B 134:T 138:L">
            <Coords points="523,491 545,491 545,501 523,501"/>
        </cell>
        <cell id="134" neighbors="123:R 133:B 135:T 137:L">
            <Coords points="523,475 545,475 545,486 523,486"/>
        </cell>
        <cell id="135" neighbors="63:T 122:R 134:B 136:L">
            <Coords points="523,459 544,459 544,469 523,469"/>
        </cell>
        <cell id="136" neighbors="64:T 135:R 137:B 151:L">
            <Coords points="474,460 495,460 495,469 474,469"/>
        </cell>
        <cell id="137" neighbors="134:R 136:T 138:B 150:L">
            <Coords points="475,475 495,475 495,485 475,485"/>
        </cell>
        <cell id="138" neighbors="133:R 137:T 139:B 149:L">
            <Coords points="475,491 495,491 495,502 475,502"/>
        </cell>
        <cell id="139" neighbors="132:R 138:T 140:B 148:L">
            <Coords points="477,506 495,506 495,516 477,516"/>
        </cell>
        <cell id="140" neighbors="131:R 139:T 141:B 147:L">
            <Coords points="479,521 496,521 496,531 479,531"/>
        </cell>
        <cell id="141" neighbors="130:R 140:T 142:B 146:L">
            <Coords points="475,537 496,537 496,549 475,549"/>
        </cell>
        <cell id="142" neighbors="129:R 141:T 143:B 145:L">
            <Coords points="464,553 495,553 495,564 464,564"/>
        </cell>
        <cell id="143" neighbors="128:R 142:T 144:L 186:B">
            <Coords points="465,569 496,569 496,579 465,579"/>
        </cell>
        <cell id="144" neighbors="143:R 145:T 156:L 184:B">
            <Coords points="417,568 447,568 447,579 417,579"/>
        </cell>
        <cell id="145" neighbors="142:R 144:B 146:T 157:L">
            <Coords points="421,553 446,553 446,563 421,563"/>
        </cell>
        <cell id="146" neighbors="141:R 145:B 147:T 158:L">
            <Coords points="426,537 447,537 447,549 426,549"/>
        </cell>
        <cell id="147" neighbors="140:R 146:B 148:T 168:L">
            <Coords points="430,522 446,522 446,531 430,531"/>
        </cell>
        <cell id="148" neighbors="139:R 147:B 149:T 153:L">
            <Coords points="429,506 448,506 448,516 429,516"/>
        </cell>
        <cell id="149" neighbors="138:R 148:B 150:T 170:L">
            <Coords points="426,491 447,491 447,502 426,502"/>
        </cell>
        <cell id="150" neighbors="137:R 149:B 151:T 152:L">
            <Coords points="426,475 447,475 447,486 426,486"/>
        </cell>
        <cell id="151" neighbors="73:T 136:R 150:B 172:L">
            <Coords points="425,459 446,459 446,469 425,469"/>
        </cell>
        <cell id="152" neighbors="77:T 150:R 153:B 171:L">
            <Coords points="376,475 398,475 398,486 376,486"/>
        </cell>
        <cell id="153" neighbors="148:R 152:T 154:L 158:B">
            <Coords points="380,505 398,505 398,515 380,515"/>
        </cell>
        <cell id="154" neighbors="81:T 153:R 155:L 159:B">
            <Coords points="337,506 348,506 348,515 337,515"/>
        </cell>
        <cell id="155" neighbors="82:T 154:R 164:B 169:L">
            <Coords points="286,504 300,504 300,516 286,516"/>
        </cell>
        <cell id="156" neighbors="144:R 157:T 161:L 182:B">
            <Coords points="372,568 398,568 398,580 372,580"/>
        </cell>
        <cell id="157" neighbors="145:R 156:B 158:T 160:L">
            <Coords points="371,553 398,553 398,563 371,563"/>
        </cell>
        <cell id="158" neighbors="146:R 153:T 157:B 159:L">
            <Coords points="377,538 398,538 398,549 377,549"/>
        </cell>
        <cell id="159" neighbors="154:T 158:R 160:B 164:L">
            <Coords points="328,538 349,538 349,549 328,549"/>
        </cell>
        <cell id="160" neighbors="157:R 159:T 161:B 163:L">
            <Coords points="323,553 349,553 349,563 323,563"/>
        </cell>
        <cell id="161" neighbors="156:R 160:T 162:L 180:B">
            <Coords points="323,568 348,568 348,579 323,579"/>
        </cell>
        <cell id="162" neighbors="161:R 163:T 165:L 178:B">
            <Coords points="273,569 299,569 299,579 273,579"/>
        </cell>
        <cell id="163" neighbors="160:R 162:B 164:T 166:L">
            <Coords points="273,553 300,553 300,563 273,563"/>
        </cell>
        <cell id="164" neighbors="155:T 159:R 163:B 167:L">
            <Coords points="279,537 299,537 299,549 279,549"/>
        </cell>
        <cell id="165" neighbors="162:R 166:T 174:B">
            <Coords points="79,569 193,569 193,580 79,580"/>
        </cell>
        <cell id="166" neighbors="163:R 165:B 167:T">
            <Coords points="92,552 201,552 201,564 92,564"/>
        </cell>
        <cell id="167" neighbors="164:R 166:B 168:T">
            <Coords points="91,537 241,537 241,548 91,548"/>
        </cell>
        <cell id="168" neighbors="147:R 167:B 169:T">
            <Coords points="90,521 238,521 238,533 90,533"/>
        </cell>
        <cell id="169" neighbors="155:R 168:B 170:T">
            <Coords points="91,505 191,505 191,516 91,516"/>
        </cell>
        <cell id="170" neighbors="149:R 169:B 171:T">
            <Coords points="91,490 149,490 149,501 91,501"/>
        </cell>
        <cell id="171" neighbors="152:R 170:B 172:T">
            <Coords points="91,474 197,474 197,487 91,487"/>
        </cell>
        <cell id="172" neighbors="151:R 171:B 173:T">
            <Coords points="92,459 176,459 176,471 92,471"/>
        </cell>
        <cell id="173" neighbors="91:T 121:R 172:B">
            <Coords points="80,430 227,430 227,453 80,453"/>
        </cell>
        <cell id="174" neighbors="165:T 175:B">
            <Coords points="91,583 176,583 176,596 91,596"/>
        </cell>
        <cell id="175" neighbors="174:T 176:B 178:R">
            <Coords points="91,599 194,599 194,611 91,611"/>
        </cell>
        <cell id="176" neighbors="175:T 177:B 179:R">
            <Coords points="78,616 142,616 142,626 78,626"/>
        </cell>
        <cell id="177" neighbors="176:T 210:R 219:B">
            <Coords points="79,631 248,631 248,655 79,655"/>
        </cell>
        <cell id="178" neighbors="162:T 175:L 179:B 180:R">
            <Coords points="274,599 300,599 300,610 274,610"/>
        </cell>
        <cell id="179" neighbors="176:L 178:T 181:R 210:B">
            <Coords points="278,615 299,615 299,627 278,627"/>
        </cell>
        <cell id="180" neighbors="161:T 178:L 181:B 182:R">
            <Coords points="323,599 349,599 349,610 323,610"/>
        </cell>
        <cell id="181" neighbors="179:L 180:T 183:R 209:B">
            <Coords points="327,616 349,616 349,626 327,626"/>
        </cell>
        <cell id="182" neighbors="156:T 180:L 183:B 184:R">
            <Coords points="367,599 397,599 397,609 367,609"/>
        </cell>
        <cell id="183" neighbors="181:L 182:T 185:R 206:B">
            <Coords points="377,616 398,616 398,627 377,627"/>
        </cell>
        <cell id="184" neighbors="144:T 182:L 185:B 186:R">
            <Coords points="416,599 447,599 447,610 416,610"/>
        </cell>
        <cell id="185" neighbors="183:L 184:T 187:R 207:B">
            <Coords points="420,616 447,616 447,626 420,626"/>
        </cell>
        <cell id="186" neighbors="143:T 184:L 187:B 188:R">
            <Coords points="464,599 496,599 496,610 464,610"/>
        </cell>
        <cell id="187" neighbors="185:L 186:T 193:R 208:B">
            <Coords points="465,615 496,615 496,626 465,626"/>
        </cell>
        <cell id="188" neighbors="128:T 186:L 189:R 193:B">
            <Coords points="514,599 545,599 545,610 514,610"/>
        </cell>
        <cell id="189" neighbors="117:T 188:L 190:R 192:B">
            <Coords points="561,600 593,600 593,611 561,611"/>
        </cell>
        <cell id="190" neighbors="118:T 189:L 191:B 195:R">
            <Coords points="608,600 640,600 640,612 608,612"/>
        </cell>
        <cell id="191" neighbors="190:T 192:L 194:R 202:B">
            <Coords points="609,616 640,616 640,627 609,627"/>
        </cell>
        <cell id="192" neighbors="189:T 191:R 193:L 203:B">
            <Coords points="561,617 593,617 593,627 561,627"/>
        </cell>
        <cell id="193" neighbors="187:L 188:T 192:R 204:B">
            <Coords points="514,616 546,616 546,626 514,626"/>
        </cell>
        <cell id="194" neighbors="191:L 195:T 197:R 201:B">
            <Coords points="657,617 689,617 689,627 657,627"/>
        </cell>
        <cell id="195" neighbors="119:T 190:L 194:B 196:R">
            <Coords points="656,601 688,601 688,612 656,612"/>
        </cell>
        <cell id="196" neighbors="120:T 195:L 197:B">
            <Coords points="705,601 737,601 737,611 705,611"/>
        </cell>
        <cell id="197" neighbors="194:L 196:T 198:B">
            <Coords points="706,616 737,616 737,627 706,627"/>
        </cell>
        <cell id="198" neighbors="197:T 199:B 201:L">
            <Coords points="706,646 738,646 738,655 706,655"/>
        </cell>
        <cell id="199" neighbors="198:T 200:L 231:B">
            <Coords points="708,677 733,677 733,687 708,687"/>
        </cell>
        <cell id="200" neighbors="199:R 201:T 211:L 230:B">
            <Coords points="660,677 683,677 683,686 660,686"/>
        </cell>
        <cell id="201" neighbors="194:T 198:R 200:B 202:L">
            <Coords points="657,646 689,646 689,655 657,655"/>
        </cell>
        <cell id="202" neighbors="191:T 201:R 203:L 211:B">
            <Coords points="610,646 641,646 641,656 610,656"/>
        </cell>
        <cell id="203" neighbors="192:T 202:R 204:L 205:B">
            <Coords points="561,645 593,645 593,656 561,656"/>
        </cell>
        <cell id="204" neighbors="193:T 203:R 205:B 208:L">
            <Coords points="514,645 546,645 546,654 514,654"/>
        </cell>
        <cell id="205" neighbors="203:T 204:T 207:T 208:T 212:B 213:B 214:B 215:B">
            <Coords points="415,659 587,659 587,670 415,670"/>
        </cell>
        <cell id="206" neighbors="183:T 207:R 209:L 216:B">
            <Coords points="368,645 398,645 398,655 368,655"/>
        </cell>
        <cell id="207" neighbors="185:T 205:B 206:L 208:R">
            <Coords points="416,644 447,644 447,655 416,655"/>
        </cell>
        <cell id="208" neighbors="187:T 204:R 205:B 207:L">
            <Coords points="465,644 495,644 495,655 465,655"/>
        </cell>
        <cell id="209" neighbors="181:T 206:R 210:L 217:B">
            <Coords points="323,645 349,645 349,655 323,655"/>
        </cell>
        <cell id="210" neighbors="177:L 179:T 209:R 218:B">
            <Coords points="274,644 300,644 300,654 274,654"/>
        </cell>
        <cell id="211" neighbors="200:R 202:T 212:L 229:B">
            <Coords points="612,677 635,677 635,686 612,686"/>
        </cell>
        <cell id="212" neighbors="205:T 211:R 213:L 228:B">
            <Coords points="564,676 588,676 588,686 564,686"/>
        </cell>
        <cell id="213" neighbors="205:T 212:R 214:L 227:B">
            <Coords points="515,676 539,676 539,686 515,686"/>
        </cell>
        <cell id="214" neighbors="205:T 213:R 215:L 226:B">
            <Coords points="467,676 489,676 489,686 467,686"/>
        </cell>
        <cell id="215" neighbors="205:T 214:R 216:L 225:B">
            <Coords points="417,676 440,676 440,685 417,685"/>
        </cell>
        <cell id="216" neighbors="206:T 215:R 217:L 224:B">
            <Coords points="368,676 393,676 393,685 368,685"/>
        </cell>
        <cell id="217" neighbors="209:T 216:R 218:L 223:B">
            <Coords points="319,676 343,676 343,686 319,686"/>
        </cell>
        <cell id="218" neighbors="210:T 217:R 222:B">
            <Coords points="270,676 294,676 294,687 270,687"/>
        </cell>
        <cell id="219" neighbors="177:T">
            <Coords points="145,667 184,667 184,679 145,679"/>
        </cell>
        <cell id="220" neighbors="221:B 222:R">
            <Coords points="78,691 146,691 146,702 78,702"/>
        </cell>
        <cell id="221" neighbors="220:T 232:B">
            <Coords points="91,706 174,706 174,719 91,719"/>
        </cell>
        <cell id="222" neighbors="218:T 220:L 223:R 246:B">
            <Coords points="276,691 300,691 300,702 276,702"/>
        </cell>
        <cell id="223" neighbors="217:T 222:L 224:R 247:B">
            <Coords points="326,691 348,691 348,702 326,702"/>
        </cell>
        <cell id="224" neighbors="216:T 223:L 225:R 248:B">
            <Coords points="375,691 399,691 399,702 375,702"/>
        </cell>
        <cell id="225" neighbors="215:T 224:L 226:R 249:B">
            <Coords points="420,692 447,692 447,702 420,702"/>
        </cell>
        <cell id="226" neighbors="214:T 225:L 227:R 250:B">
            <Coords points="468,692 496,692 496,702 468,702"/>
        </cell>
        <cell id="227" neighbors="213:T 226:L 228:R 251:B">
            <Coords points="516,691 545,691 545,702 516,702"/>
        </cell>
        <cell id="228" neighbors="212:T 227:L 229:R 252:B">
            <Coords points="565,693 593,693 593,703 565,703"/>
        </cell>
        <cell id="229" neighbors="211:T 228:L 230:R 253:B">
            <Coords points="613,693 641,693 641,702 613,702"/>
        </cell>
        <cell id="230" neighbors="200:T 229:L 231:R 254:B">
            <Coords points="661,692 688,692 688,702 661,702"/>
        </cell>
        <cell id="231" neighbors="199:T 230:L 255:B">
            <Coords points="709,692 737,692 737,702 709,702"/>
        </cell>
        <cell id="232" neighbors="221:T 233:B">
            <Coords points="79,722 164,722 164,733 79,733"/>
        </cell>
        <cell id="233" neighbors="232:T 234:B 246:R">
            <Coords points="91,738 237,738 237,750 91,750"/>
        </cell>
        <cell id="234" neighbors="233:T 235:B 256:R">
            <Coords points="91,754 155,754 155,765 91,765"/>
        </cell>
        <cell id="235" neighbors="234:T 236:B">
            <Coords points="92,770 230,770 230,781 92,781"/>
        </cell>
        <cell id="236" neighbors="235:T 237:B 259:R">
            <Coords points="104,785 197,785 197,797 104,797"/>
        </cell>
        <cell id="237" neighbors="236:T 238:B 262:R">
            <Coords points="104,801 140,801 140,812 104,812"/>
        </cell>
        <cell id="238" neighbors="237:T 239:B 268:R">
            <Coords points="103,816 160,816 160,828 103,828"/>
        </cell>
        <cell id="239" neighbors="238:T 240:B 265:R">
            <Coords points="103,831 202,831 202,845 103,845"/>
        </cell>
        <cell id="240" neighbors="239:T 241:B 286:R">
            <Coords points="103,848 170,848 170,859 103,859"/>
        </cell>
        <cell id="241" neighbors="240:T 242:B 274:R">
            <Coords points="102,864 226,864 226,876 102,876"/>
        </cell>
        <cell id="242" neighbors="241:T 243:B 275:R">
            <Coords points="102,878 212,878 212,890 102,890"/>
        </cell>
        <cell id="243" neighbors="242:T 244:B 276:R">
            <Coords points="103,894 200,894 200,907 103,907"/>
        </cell>
        <cell id="244" neighbors="243:T 245:B 277:R">
            <Coords points="103,910 220,910 220,921 103,921"/>
        </cell>
        <cell id="245" neighbors="244:T 301:R">
            <Coords points="79,926 227,926 227,949 79,949"/>
        </cell>
        <cell id="246" neighbors="222:T 233:L 247:R 259:B">
            <Coords points="270,738 300,738 300,748 270,748"/>
        </cell>
        <cell id="247" neighbors="223:T 246:L 248:R 260:B">
            <Coords points="320,738 350,738 350,748 320,748"/>
        </cell>
        <cell id="248" neighbors="224:T 247:L 249:R 261:B">
            <Coords points="370,737 399,737 399,748 370,748"/>
        </cell>
        <cell id="249" neighbors="225:T 248:L 250:R 256:B">
            <Coords points="419,739 448,739 448,748 419,748"/>
        </cell>
        <cell id="250" neighbors="226:T 249:L 251:R 257:B">
            <Coords points="468,738 497,738 497,748 468,748"/>
        </cell>
        <cell id="251" neighbors="227:T 250:L 252:R 258:B">
            <Coords points="516,737 545,737 545,748 516,748"/>
        </cell>
        <cell id="252" neighbors="228:T 251:L 253:R 301:B">
            <Coords points="564,739 595,739 595,749 564,749"/>
        </cell>
        <cell id="253" neighbors="229:T 252:L 254:R 302:B">
            <Coords points="612,739 642,739 642,749 612,749"/>
        </cell>
        <cell id="254" neighbors="230:T 253:L 255:R 303:B">
            <Coords points="661,739 689,739 689,749 661,749"/>
        </cell>
        <cell id="255" neighbors="231:T 254:L 304:B">
            <Coords points="707,738 738,738 738,750 707,750"/>
        </cell>
        <cell id="256" neighbors="234:L 249:T 257:R 262:B">
            <Coords points="423,753 447,753 447,764 423,764"/>
        </cell>
        <cell id="257" neighbors="250:T 256:L 258:R 263:B">
            <Coords points="467,754 497,754 497,765 467,765"/>
        </cell>
        <cell id="258" neighbors="251:T 257:L 264:B">
            <Coords points="517,753 545,753 545,764 517,764"/>
        </cell>
        <cell id="259" neighbors="236:L 246:T 260:R 265:B">
            <Coords points="277,784 301,784 301,797 277,797"/>
        </cell>
        <cell id="260" neighbors="247:T 259:L 261:R 266:B">
            <Coords points="321,785 349,785 349,796 321,796"/>
        </cell>
        <cell id="261" neighbors="248:T 260:L 267:B">
            <Coords points="374,786 399,786 399,796 374,796"/>
        </cell>
        <cell id="262" neighbors="237:L 256:T 263:R 268:B">
            <Coords points="420,801 449,801 449,812 420,812"/>
        </cell>
        <cell id="263" neighbors="257:T 262:L 264:R 269:B">
            <Coords points="468,801 497,801 497,812 468,812"/>
        </cell>
        <cell id="264" neighbors="258:T 263:L 270:B">
            <Coords points="515,801 546,801 546,812 515,812"/>
        </cell>
        <cell id="265" neighbors="239:L 259:T 266:R 274:B">
            <Coords points="272,832 301,832 301,843 272,843"/>
        </cell>
        <cell id="266" neighbors="260:T 265:L 267:R 279:B">
            <Coords points="321,832 349,832 349,843 321,843"/>
        </cell>
        <cell id="267" neighbors="261:T 266:L 273:R 282:B">
            <Coords points="370,833 399,833 399,843 370,843"/>
        </cell>
        <cell id="268" neighbors="238:L 262:T 269:R 273:B">
            <Coords points="420,817 448,817 448,828 420,828"/>
        </cell>
        <cell id="269" neighbors="263:T 268:L 270:R 272:B">
            <Coords points="468,816 496,816 496,827 468,827"/>
        </cell>
        <cell id="270" neighbors="264:T 269:L 271:B">
            <Coords points="517,817 545,817 545,828 517,828"/>
        </cell>
        <cell id="271" neighbors="270:T 272:L 288:B">
            <Coords points="516,832 546,832 546,843 516,843"/>
        </cell>
        <cell id="272" neighbors="269:T 271:R 273:L 287:B">
            <Coords points="468,833 495,833 495,843 468,843"/>
        </cell>
        <cell id="273" neighbors="267:L 268:T 272:R 286:B">
            <Coords points="418,832 447,832 447,843 418,843"/>
        </cell>
        <cell id="274" neighbors="241:L 265:T 275:B 279:R">
            <Coords points="272,863 299,863 299,875 272,875"/>
        </cell>
        <cell id="275" neighbors="242:L 274:T 276:B 278:R">
            <Coords points="278,880 300,880 300,892 278,892"/>
        </cell>
        <cell id="276" neighbors="243:L 275:T 277:B 280:R">
            <Coords points="278,896 300,896 300,907 278,907"/>
        </cell>
        <cell id="277" neighbors="244:L 276:T 281:R">
            <Coords points="277,910 300,910 300,921 277,921"/>
        </cell>
        <cell id="278" neighbors="275:L 279:T 280:B 283:R">
            <Coords points="320,880 341,880 341,890 320,890"/>
        </cell>
        <cell id="279" neighbors="266:T 274:L 278:B 282:R">
            <Coords points="321,863 349,863 349,874 321,874"/>
        </cell>
        <cell id="280" neighbors="276:L 278:T 281:B 284:R">
            <Coords points="321,895 342,895 342,907 321,907"/>
        </cell>
        <cell id="281" neighbors="277:L 280:T 285:R">
            <Coords points="326,911 351,911 351,921 326,921"/>
        </cell>
        <cell id="282" neighbors="267:T 279:L 283:B 291:R">
            <Coords points="370,863 399,863 399,875 370,875"/>
        </cell>
        <cell id="283" neighbors="278:L 282:T 284:B 292:R">
            <Coords points="377,879 399,879 399,890 377,890"/>
        </cell>
        <cell id="284" neighbors="280:L 283:T 285:B 295:R">
            <Coords points="376,895 399,895 399,907 376,907"/>
        </cell>
        <cell id="285" neighbors="281:L 284:T 296:R">
            <Coords points="377,911 399,911 399,922 377,922"/>
        </cell>
        <cell id="286" neighbors="240:L 273:T 287:R 291:B">
            <Coords points="423,848 446,848 446,859 423,859"/>
        </cell>
        <cell id="287" neighbors="272:T 286:L 288:R 290:B">
            <Coords points="468,849 495,849 495,859 468,859"/>
        </cell>
        <cell id="288" neighbors="271:T 287:L 289:B">
            <Coords points="517,849 545,849 545,859 517,859"/>
        </cell>
        <cell id="289" neighbors="288:T 290:L 294:B">
            <Coords points="516,864 546,864 546,874 516,874"/>
        </cell>
        <cell id="290" neighbors="287:T 289:R 291:L 293:B">
            <Coords points="469,863 496,863 496,874 469,874"/>
        </cell>
        <cell id="291" neighbors="282:L 286:T 290:R 292:B">
            <Coords points="420,864 448,864 448,874 420,874"/>
        </cell>
        <cell id="292" neighbors="283:L 291:T 293:R 295:B">
            <Coords points="424,880 447,880 447,891 424,891"/>
        </cell>
        <cell id="293" neighbors="290:T 292:L 294:R 298:B">
            <Coords points="474,879 496,879 496,890 474,890"/>
        </cell>
        <cell id="294" neighbors="289:T 293:L 299:B">
            <Coords points="523,879 545,879 545,891 523,891"/>
        </cell>
        <cell id="295" neighbors="284:L 292:T 296:B 298:R">
            <Coords points="425,895 447,895 447,906 425,906"/>
        </cell>
        <cell id="296" neighbors="285:L 295:T 297:R">
            <Coords points="425,910 448,910 448,922 425,922"/>
        </cell>
        <cell id="297" neighbors="296:L 298:T 300:R">
            <Coords points="475,911 495,911 495,922 475,922"/>
        </cell>
        <cell id="298" neighbors="293:T 295:L 297:B 299:R">
            <Coords points="474,896 495,896 495,907 474,907"/>
        </cell>
        <cell id="299" neighbors="294:T 298:L 300:B">
            <Coords points="522,896 544,896 544,907 522,907"/>
        </cell>
        <cell id="300" neighbors="297:L 299:T">
            <Coords points="523,911 545,911 545,923 523,923"/>
        </cell>
        <cell id="301" neighbors="245:L 252:T 302:R">
            <Coords points="565,941 594,941 594,951 565,951"/>
        </cell>
        <cell id="302" neighbors="253:T 301:L 303:R">
            <Coords points="613,941 641,941 641,952 613,952"/>
        </cell>
        <cell id="303" neighbors="254:T 302:L 304:R">
            <Coords points="660,941 689,941 689,951 660,951"/>
        </cell>
        <cell id="304" neighbors="255:T 303:L">
            <Coords points="709,941 738,941 738,951 709,951"/>
        </cell>
    </table>
</document>
